getversion/__init__.py
getversion/getversion.py
getversionpkg-0.5.dist-info/METADATA
getversionpkg-0.5.dist-info/WHEEL
getversionpkg-0.5.dist-info/top_level.txt
getversionpkg-0.5.dist-info/RECORD
