Metadata-Version: 2.1
Name: getversionpkg
Version: 0.5
Summary: This is a tesp package
Requires-Python: >=3.6
